gitcli/__init__.py
gitcli/cli.py
gitcli/git_advanced.py
gitcli/git_branches.py
gitcli/git_operations.py
gitcli/helpers.py
gitcli_automation-1.0.2.dist-info/licenses/LICENSE
gitcli_automation-1.0.2.dist-info/METADATA
gitcli_automation-1.0.2.dist-info/WHEEL
gitcli_automation-1.0.2.dist-info/entry_points.txt
gitcli_automation-1.0.2.dist-info/top_level.txt
gitcli_automation-1.0.2.dist-info/RECORD
