Metadata-Version: 2.4
Name: gitcli-automation
Version: 1.0.2
Summary: User-friendly command-line tool for Git that simplifies everyday operations. Perfect for developers who want powerful Git functionality without the complexity.
Home-page: https://github.com/Adelodunpeter25/GitCLI
Author: Adelodunpeter
Author-email: Adelodun Peter <adelodunpeter24@gmail.com>
License: MIT
Project-URL: Homepage, https://github.com/Adelodunpeter25/GitCLI
Project-URL: Bug Reports, https://github.com/Adelodunpeter25/issues
Project-URL: Source, https://github.com/Adelodunpeter25/GitCLI
Keywords: git,cli,automation,tool,interactive,version-control
Classifier: Development Status :: 4 - Beta
Classifier: Intended Audience :: Developers
Classifier: Topic :: Software Development :: Version Control :: Git
Classifier: License :: OSI Approved :: MIT License
Classifier: Programming Language :: Python :: 3
Requires-Python: >=3.7
License-File: LICENSE
Requires-Dist: colorama>=0.4.6
Requires-Dist: yaspin>=2.3.0
Provides-Extra: windows
Requires-Dist: win10toast>=0.9; extra == "windows"
Dynamic: author
Dynamic: home-page
Dynamic: license-file
Dynamic: requires-python
